cfc_model.py
cfc_model/__init__.py
cfc_model/configuration.py
cfc_model/data_types.py
cfc_model/dense_models.py
cfc_model/tf_cfc.py
cfc_model/torch_cfc.py
cfc_model/adapters/__init__.py
cfc_model/adapters/irregular_sampled_datasets.py
cfc_model/config/default.json
cfc_model/duv/__init__.py
cfc_model/duv/duv_person_activity.py
cfc_model/duv/duv_physionet.py
cfc_model/duv/duv_utils.py
cfc_model/figure_1_experiments/Closed_form_solution_neuron.m
cfc_model/figure_1_experiments/figure_1_data.mat
cfc_model/figure_1_experiments/main.m
cfc_model/figure_1_experiments/neuron.m
cfc_model/figure_1_experiments/presynaptic_neurons_parameter.m
cfc_model/tests/__init__.py
cfc_model/tests/test_configuration.py
cfc_model/tests/test_data_types.py
cfc_model/tests/test_dense_models.py
cfc_model/tests/traffic_with_cfc.py
cfc_model/tests/train_et_smnist.py
cfc_model/tests/train_imdb.py
cfc_model/tests/train_person_acitivity.py
cfc_model/tests/train_physio.py
cfc_model/tests/train_walker.py
cfc_model/tests/train_xor.py
cfc_model-1.1.4.dist-info/LICENSE
cfc_model-1.1.4.dist-info/METADATA
cfc_model-1.1.4.dist-info/WHEEL
cfc_model-1.1.4.dist-info/top_level.txt
cfc_model-1.1.4.dist-info/RECORD
