Metadata-Version: 2.1
Name: cfc-model
Version: 1.1.4
Summary: An easy-to-use api for the closed-form continuous models in tensorflow
Home-page: https://github.com/nightvision04/CfC
Author: Daniel Scott
Author-email: danscottlearns@gmail.com
License: Apache
Classifier: Development Status :: 4 - Beta
Classifier: License :: OSI Approved :: Apache Software License
Classifier: Topic :: Scientific/Engineering
Classifier: Operating System :: Microsoft :: Windows
Classifier: Operating System :: POSIX :: Linux
Classifier: Operating System :: MacOS
Classifier: Programming Language :: Python
Classifier: Programming Language :: Python :: 3
Classifier: Programming Language :: Python :: 3.7
Classifier: Programming Language :: Python :: 3.8
Classifier: Programming Language :: Python :: 3.9
Classifier: Programming Language :: Python :: 3.10
License-File: LICENSE
Requires-Dist: pandas
Requires-Dist: numpy
